{
  "AK.BMR.BXY": {
    "weight": 0.0552903578781822
  }, 
  "AK.BPAW.BXY": {
    "weight": 0.04789569607884362
  }, 
  "AK.BRLK.BXY": {
    "weight": 0.05215320101349114
  }, 
  "AK.BWN.BXY": {
    "weight": 0.04332871020736484
  }, 
  "AK.CAST.BXY": {
    "weight": 0.05200462264913768
  }, 
  "AK.CCB.BXY": {
    "weight": 0.044525014612748354
  }, 
  "AK.CNP.BXY": {
    "weight": 0.054835859684689216
  }, 
  "AK.COLD.BXY": {
    "weight": 0.06908340693578605
  }, 
  "AK.DCPH.BXY": {
    "weight": 0.155798478274294
  }, 
  "AK.DDM.BXY": {
    "weight": 0.04655525220028844
  }, 
  "AK.DIV.BXY": {
    "weight": 0.048325924630095184
  }, 
  "AK.DOT.BXY": {
    "weight": 0.056720910497215025
  }, 
  "AK.EYAK.BXY": {
    "weight": 0.05081539529819373
  }, 
  "AK.FYU.BXY": {
    "weight": 0.0672462992962545
  }, 
  "AK.KLU.BXY": {
    "weight": 0.046656538636800596
  }, 
  "AK.MCK.BXY": {
    "weight": 0.041835232529464784
  }, 
  "AK.MDM.BXY": {
    "weight": 0.04563728251769432
  }, 
  "AK.MLY.BXY": {
    "weight": 0.050976766124117306
  }, 
  "AK.PAX.BXY": {
    "weight": 0.04711291571741065
  }, 
  "AK.PPLA.BXY": {
    "weight": 0.0517317319160721
  }, 
  "AK.RAG.BXY": {
    "weight": 0.05773220391207379
  }, 
  "AK.RND.BXY": {
    "weight": 0.04122055280817242
  }, 
  "AK.SCM.BXY": {
    "weight": 0.04212463595218626
  }, 
  "AK.SCRK.BXY": {
    "weight": 0.05832074392328448
  }, 
  "AK.SSN.BXY": {
    "weight": 0.04520881066644511
  }, 
  "AK.SWD.BXY": {
    "weight": 0.046976412211214146
  }, 
  "AK.TNA.BXY": {
    "weight": 0.9705296350408632
  }, 
  "AK.TRF.BXY": {
    "weight": 0.043719735944794696
  }, 
  "AK.UNV.BXY": {
    "weight": 0.9227666097439186
  }, 
  "AK.WRH.BXY": {
    "weight": 0.0437010081345325
  }, 
  "AT.CRAG.BXY": {
    "weight": 0.21889087734425045
  }, 
  "AT.MID.BXY": {
    "weight": 0.05544034341114522
  }, 
  "AT.OHAK.BXY": {
    "weight": 0.09767113307945809
  }, 
  "AT.PMR.BXY": {
    "weight": 0.0417685519116574
  }, 
  "AT.SIT.BXY": {
    "weight": 0.1864838347590734
  }, 
  "AT.SKAG.BXY": {
    "weight": 0.1782599474606627
  }, 
  "AT.SVW2.BXY": {
    "weight": 0.0987194788039044
  }, 
  "AU.ARMA.BXY": {
    "weight": 0.31840985729873084
  }, 
  "AU.BBOO.BXY": {
    "weight": 0.8471151214820712
  }, 
  "AU.BLDU.BXY": {
    "weight": 0.28260876492105047
  }, 
  "AU.CMSA.BXY": {
    "weight": 0.29248007572567103
  }, 
  "AU.CNB.BXY": {
    "weight": 0.2518070444928173
  }, 
  "AU.COEN.BXY": {
    "weight": 0.511888736728705
  }, 
  "AU.CTA.BXY": {
    "weight": 0.35036472959759407
  }, 
  "AU.EIDS.BXY": {
    "weight": 0.3998750272739431
  }, 
  "AU.GIRL.BXY": {
    "weight": 0.45228520784995174
  }, 
  "AU.KNRA.BXY": {
    "weight": 0.5094924218417112
  }, 
  "AU.LHI.BXY": {
    "weight": 0.6996684332474676
  }, 
  "AU.MANU.BXY": {
    "weight": 0.5968968374476609
  }, 
  "AU.MCQ.BXY": {
    "weight": 0.9992696420407443
  }, 
  "AU.MEEK.BXY": {
    "weight": 0.29873349385419157
  }, 
  "AU.MOO.BXY": {
    "weight": 0.34280842758684926
  }, 
  "AU.MORW.BXY": {
    "weight": 0.27508720794822933
  }, 
  "AU.MTN.BXY": {
    "weight": 0.5347271466551761
  }, 
  "AU.NFK.BXY": {
    "weight": 0.9151364095296963
  }, 
  "AU.NIUE.BXY": {
    "weight": 0.6742702943540668
  }, 
  "AU.QLP.BXY": {
    "weight": 0.38495717530875667
  }, 
  "AU.RABL.BXY": {
    "weight": 0.5676539987071224
  }, 
  "AU.TOO.BXY": {
    "weight": 0.28234388437618324
  }, 
  "AU.XMIS.BXY": {
    "weight": 0.9981488535522656
  }, 
  "AV.AUL.BXY": {
    "weight": 0.07168605542317
  }, 
  "AV.SPCG.BXY": {
    "weight": 0.05133500608983742
  }, 
  "AZ.BZN.BXY": {
    "weight": 0.015626869494132275
  }, 
  "AZ.CRY.BXY": {
    "weight": 0.015615320666808378
  }, 
  "AZ.FRD.BXY": {
    "weight": 0.015578404618641455
  }, 
  "AZ.KNW.BXY": {
    "weight": 0.015482227154068483
  }, 
  "AZ.LVA2.BXY": {
    "weight": 0.01568361132542837
  }, 
  "AZ.MONP2.BXY": {
    "weight": 0.016129391360395397
  }, 
  "AZ.RDM.BXY": {
    "weight": 0.01564835961648066
  }, 
  "AZ.SMER.BXY": {
    "weight": 0.01607395081004335
  }, 
  "AZ.SND.BXY": {
    "weight": 0.015536964771966448
  }, 
  "AZ.TRO.BXY": {
    "weight": 0.015437246750618173
  }, 
  "AZ.WMC.BXY": {
    "weight": 0.015562774553358135
  }, 
  "CI.ADO.BXY": {
    "weight": 0.015773969408514235
  }, 
  "CI.BAK.BXY": {
    "weight": 0.018621105721085236
  }, 
  "CI.BAR.BXY": {
    "weight": 0.016611647426113603
  }, 
  "CI.BBR.BXY": {
    "weight": 0.015358435894510714
  }, 
  "CI.BC3.BXY": {
    "weight": 0.014848386734358614
  }, 
  "CI.BEL.BXY": {
    "weight": 0.014868985077301444
  }, 
  "CI.BFS.BXY": {
    "weight": 0.016102469131612257
  }, 
  "CI.CWC.BXY": {
    "weight": 0.017506728926195446
  }, 
  "CI.DEC.BXY": {
    "weight": 0.017052758412441443
  }, 
  "CI.DJJ.BXY": {
    "weight": 0.017320118414149054
  }, 
  "CI.DVT.BXY": {
    "weight": 0.016280367151695195
  }, 
  "CI.EDW2.BXY": {
    "weight": 0.016457514311844588
  }, 
  "CI.FMP.BXY": {
    "weight": 0.017290829800476405
  }, 
  "CI.GLA.BXY": {
    "weight": 0.01522450180887751
  }, 
  "CI.GMR.BXY": {
    "weight": 0.014470181957712224
  }, 
  "CI.GSC.BXY": {
    "weight": 0.015255846275570332
  }, 
  "CI.HEC.BXY": {
    "weight": 0.014844479284402882
  }, 
  "CI.IRM.BXY": {
    "weight": 0.01441515616416795
  }, 
  "CI.ISA.BXY": {
    "weight": 0.017502766889881706
  }, 
  "CI.LGU.BXY": {
    "weight": 0.018558420504547
  }, 
  "CI.LRL.BXY": {
    "weight": 0.016215477305792703
  }, 
  "CI.MLAC.BXY": {
    "weight": 0.02066470644200661
  }, 
  "CI.MPM.BXY": {
    "weight": 0.016344048636826383
  }, 
  "CI.MPP.BXY": {
    "weight": 0.020425937947977302
  }, 
  "CI.MUR.BXY": {
    "weight": 0.015974482230539152
  }, 
  "CI.MWC.BXY": {
    "weight": 0.016635858316868708
  }, 
  "CI.OSI.BXY": {
    "weight": 0.01767667133483823
  }, 
  "CI.PASC.BXY": {
    "weight": 0.016846309511098494
  }, 
  "CI.PDM.BXY": {
    "weight": 0.013935812247610603
  }, 
  "CI.PLM.BXY": {
    "weight": 0.015904258553733654
  }, 
  "CI.RPV.BXY": {
    "weight": 0.01745424894834334
  }, 
  "CI.SBC.BXY": {
    "weight": 0.020160216193443478
  }, 
  "CI.SCI2.BXY": {
    "weight": 0.018564477542443242
  }, 
  "CI.SDD.BXY": {
    "weight": 0.016519016671334662
  }, 
  "CI.SHO.BXY": {
    "weight": 0.015113397054418162
  }, 
  "CI.SMM.BXY": {
    "weight": 0.021138038750031944
  }, 
  "CI.SVD.BXY": {
    "weight": 0.015570903274354113
  }, 
  "CI.SWS.BXY": {
    "weight": 0.01572445491194557
  }, 
  "CI.TIN.BXY": {
    "weight": 0.018517323957994762
  }, 
  "CI.TUQ.BXY": {
    "weight": 0.014684139009386575
  }, 
  "CI.USC.BXY": {
    "weight": 0.01707817967162785
  }, 
  "CI.VCS.BXY": {
    "weight": 0.016652646562300512
  }, 
  "CN.BBB.BXY": {
    "weight": 0.2147002248667974
  }, 
  "CN.DRLN.BXY": {
    "weight": 0.9550552010901836
  }, 
  "CN.INK.BXY": {
    "weight": 0.6208020464769703
  }, 
  "CN.LLLB.BXY": {
    "weight": 0.06449651106652102
  }, 
  "CN.RES.BXY": {
    "weight": 0.9999999525490284
  }, 
  "CN.SCHQ.BXY": {
    "weight": 0.8788368513213636
  }, 
  "CN.ULM.BXY": {
    "weight": 0.06485536967028703
  }, 
  "CN.WHY.BXY": {
    "weight": 0.19426948673999098
  }, 
  "CU.BBGH.BXY": {
    "weight": 0.5311648068954367
  }, 
  "CU.GTBY.BXY": {
    "weight": 0.965837781288852
  }, 
  "CU.TGUH.BXY": {
    "weight": 0.4869480366016984
  }, 
  "EP.KIDD.BXY": {
    "weight": 0.009433987664575335
  }, 
  "G.CAN.BXY": {
    "weight": 0.24742221966086791
  }, 
  "G.CLF.BXY": {
    "weight": 0.3361965777537056
  }, 
  "G.DRV.BXY": {
    "weight": 0.9999798504590655
  }, 
  "G.ECH.BXY": {
    "weight": 0.14970560628363727
  }, 
  "G.FDF.BXY": {
    "weight": 0.5277486946175681
  }, 
  "G.FOMA.BXY": {
    "weight": 0.7352518449215957
  }, 
  "G.HDC.BXY": {
    "weight": 0.4008092088998329
  }, 
  "G.INU.BXY": {
    "weight": 0.3565978604987872
  }, 
  "G.MBO.BXY": {
    "weight": 0.9973155184290486
  }, 
  "G.PPTF.BXY": {
    "weight": 0.9667643146997801
  }, 
  "G.TAM.BXY": {
    "weight": 0.999725276121109
  }, 
  "G.UNM.BXY": {
    "weight": 0.4766338447508241
  }, 
  "GE.EIL.BXY": {
    "weight": 0.9344799704322438
  }, 
  "GE.SNAA.BXY": {
    "weight": 1.0
  }, 
  "GE.SUMG.BXY": {
    "weight": 0.9999623616643112
  }, 
  "GE.SUW.BXY": {
    "weight": 0.6832843996153427
  }, 
  "GE.TIRR.BXY": {
    "weight": 0.4162666803101044
  }, 
  "GT.BOSA.BXY": {
    "weight": 0.4799605708447782
  }, 
  "GT.DBIC.BXY": {
    "weight": 0.9971546488401473
  }, 
  "GT.LBTB.BXY": {
    "weight": 0.52354488099743
  }, 
  "GT.LPAZ.BXY": {
    "weight": 0.7164003145996473
  }, 
  "GT.VNDA.BXY": {
    "weight": 0.9431832785394472
  }, 
  "HW.CCRK.BXY": {
    "weight": 0.03361498208038737
  }, 
  "HW.DDRF.BXY": {
    "weight": 0.03271877317801858
  }, 
  "HW.PHIN.BXY": {
    "weight": 0.03254976483342611
  }, 
  "IC.BJT.BXY": {
    "weight": 0.9384158219293693
  }, 
  "IC.HIA.BXY": {
    "weight": 0.91460320528069
  }, 
  "IC.KMI.BXY": {
    "weight": 0.7668557518488194
  }, 
  "IC.LSA.BXY": {
    "weight": 0.9830714595115753
  }, 
  "IC.MDJ.BXY": {
    "weight": 0.9166299028899356
  }, 
  "IC.QIZ.BXY": {
    "weight": 0.7948069475392165
  }, 
  "II.AAK.BXY": {
    "weight": 0.08877493479291558
  }, 
  "II.ABPO.BXY": {
    "weight": 0.7350369022486954
  }, 
  "II.ALE.BXY": {
    "weight": 0.9999999954131662
  }, 
  "II.ARU.BXY": {
    "weight": 0.6187194414059657
  }, 
  "II.ASCN.BXY": {
    "weight": 0.9998363251945992
  }, 
  "II.BFO.BXY": {
    "weight": 0.1375409810561474
  }, 
  "II.BORG.BXY": {
    "weight": 0.9999623660702116
  }, 
  "II.BRVK.BXY": {
    "weight": 0.22522555358334476
  }, 
  "II.EFI.BXY": {
    "weight": 0.9942890458463526
  }, 
  "II.JTS.BXY": {
    "weight": 0.38685287096241927
  }, 
  "II.KDAK.BXY": {
    "weight": 0.08075149431112381
  }, 
  "II.KIV.BXY": {
    "weight": 0.6111929579230828
  }, 
  "II.KURK.BXY": {
    "weight": 0.3609565121660483
  }, 
  "II.MBAR.BXY": {
    "weight": 0.986244409650678
  }, 
  "II.MSEY.BXY": {
    "weight": 0.9996142467456947
  }, 
  "II.MSVF.BXY": {
    "weight": 0.8819643752228318
  }, 
  "II.OBN.BXY": {
    "weight": 0.8744857783510623
  }, 
  "II.PFO.BXY": {
    "weight": 0.015384455637096171
  }, 
  "II.RPN.BXY": {
    "weight": 0.9999999999999447
  }, 
  "II.SUR.BXY": {
    "weight": 0.6704700165429951
  }, 
  "II.TAU.BXY": {
    "weight": 0.3608698812798755
  }, 
  "II.TLY.BXY": {
    "weight": 0.9992836448067484
  }, 
  "II.UOSS.BXY": {
    "weight": 0.9993453163431434
  }, 
  "II.WRAB.BXY": {
    "weight": 0.6589301098571828
  }, 
  "IU.ADK.BXY": {
    "weight": 0.9559238918968409
  }, 
  "IU.AFI.BXY": {
    "weight": 0.6543561628971787
  }, 
  "IU.ANMO.BXY": {
    "weight": 0.007147727950894757
  }, 
  "IU.ANTO.BXY": {
    "weight": 0.6249054366980294
  }, 
  "IU.BBSR.BXY": {
    "weight": 0.97883911767337
  }, 
  "IU.BILL.BXY": {
    "weight": 0.99973842005653
  }, 
  "IU.CASY.BXY": {
    "weight": 0.9999999999853626
  }, 
  "IU.CHTO.BXY": {
    "weight": 0.8004388898472813
  }, 
  "IU.COLA.BXY": {
    "weight": 0.04542588053233297
  }, 
  "IU.COR.BXY": {
    "weight": 0.0440125482869129
  }, 
  "IU.CTAO.BXY": {
    "weight": 0.35036793199062927
  }, 
  "IU.DAV.BXY": {
    "weight": 0.9984974680368438
  }, 
  "IU.FUNA.BXY": {
    "weight": 0.8454978646156268
  }, 
  "IU.FURI.BXY": {
    "weight": 0.9879016340257172
  }, 
  "IU.GNI.BXY": {
    "weight": 0.6233055516318768
  }, 
  "IU.GRFO.BXY": {
    "weight": 0.15221491194482467
  }, 
  "IU.HKT.BXY": {
    "weight": 0.03307906005973797
  }, 
  "IU.HNR.BXY": {
    "weight": 0.9159502930228163
  }, 
  "IU.KBL.BXY": {
    "weight": 0.5841295981638578
  }, 
  "IU.KBS.BXY": {
    "weight": 0.9998476305754951
  }, 
  "IU.KEV.BXY": {
    "weight": 0.9991499403008983
  }, 
  "IU.KIEV.BXY": {
    "weight": 0.5513456814590936
  }, 
  "IU.KIP.BXY": {
    "weight": 0.563620913563349
  }, 
  "IU.KNTN.BXY": {
    "weight": 0.9370432960019739
  }, 
  "IU.KONO.BXY": {
    "weight": 0.8774279983759079
  }, 
  "IU.LCO.BXY": {
    "weight": 0.03734564394831979
  }, 
  "IU.LSZ.BXY": {
    "weight": 0.9208021434873646
  }, 
  "IU.LVC.BXY": {
    "weight": 0.1652643337326174
  }, 
  "IU.MAJO.BXY": {
    "weight": 0.3308319321879991
  }, 
  "IU.MBWA.BXY": {
    "weight": 0.4916428943667747
  }, 
  "IU.MIDW.BXY": {
    "weight": 0.9999281802450111
  }, 
  "IU.NWAO.BXY": {
    "weight": 0.35301812590795595
  }, 
  "IU.OTAV.BXY": {
    "weight": 0.9258048784122409
  }, 
  "IU.PAB.BXY": {
    "weight": 0.31422279858254837
  }, 
  "IU.PAYG.BXY": {
    "weight": 0.9563945202530446
  }, 
  "IU.PET.BXY": {
    "weight": 0.9994303916358795
  }, 
  "IU.PMG.BXY": {
    "weight": 0.5355717281599812
  }, 
  "IU.PMSA.BXY": {
    "weight": 0.9974174719436538
  }, 
  "IU.POHA.BXY": {
    "weight": 0.5635943272769904
  }, 
  "IU.QSPA.BXY": {
    "weight": 0.4959056621294563
  }, 
  "IU.RAR.BXY": {
    "weight": 0.9232066489042554
  }, 
  "IU.RSSD.BXY": {
    "weight": 0.008452197660335553
  }, 
  "IU.SDV.BXY": {
    "weight": 0.9167606020886425
  }, 
  "IU.SLBS.BXY": {
    "weight": 0.14271188944866295
  }, 
  "IU.SNZO.BXY": {
    "weight": 0.9963862240374795
  }, 
  "IU.SSPA.BXY": {
    "weight": 0.1711864090297762
  }, 
  "IU.TARA.BXY": {
    "weight": 0.9798494787099401
  }, 
  "IU.TATO.BXY": {
    "weight": 0.1352422727083458
  }, 
  "IU.TIXI.BXY": {
    "weight": 0.9351269330459487
  }, 
  "IU.TRQA.BXY": {
    "weight": 0.1915822496455806
  }, 
  "IU.TSUM.BXY": {
    "weight": 0.9051227324653812
  }, 
  "IU.TUC.BXY": {
    "weight": 0.013400356377240644
  }, 
  "IU.WAKE.BXY": {
    "weight": 0.9999024647272013
  }, 
  "IU.WCI.BXY": {
    "weight": 0.10777156579220791
  }, 
  "IU.WVT.BXY": {
    "weight": 0.09618023314213607
  }, 
  "IU.XMAS.BXY": {
    "weight": 0.9983931894601716
  }, 
  "IU.YAK.BXY": {
    "weight": 0.9344971481030616
  }, 
  "IU.YSS.BXY": {
    "weight": 0.5373962095318681
  }, 
  "IW.DLMT.BXY": {
    "weight": 0.019126612231539383
  }, 
  "IW.FLWY.BXY": {
    "weight": 0.013117092122598704
  }, 
  "IW.FXWY.BXY": {
    "weight": 0.013291675625663673
  }, 
  "IW.IMW.BXY": {
    "weight": 0.013369973343925833
  }, 
  "IW.LOHW.BXY": {
    "weight": 0.012518250592296505
  }, 
  "IW.MFID.BXY": {
    "weight": 0.024114030224178688
  }, 
  "IW.MOOW.BXY": {
    "weight": 0.012880638881852563
  }, 
  "IW.PHWY.BXY": {
    "weight": 0.007054881041668552
  }, 
  "IW.PLID.BXY": {
    "weight": 0.026850031171958035
  }, 
  "IW.REDW.BXY": {
    "weight": 0.012741159129206314
  }, 
  "IW.RRI2.BXY": {
    "weight": 0.01359576148198444
  }, 
  "IW.RWWY.BXY": {
    "weight": 0.007824320867797201
  }, 
  "IW.SMCO.BXY": {
    "weight": 0.007100574691057703
  }, 
  "IW.SNOW.BXY": {
    "weight": 0.012653142817437176
  }, 
  "IW.TPAW.BXY": {
    "weight": 0.013023065863404798
  }, 
  "JP.ASAJ.BXY": {
    "weight": 0.47724546413693913
  }, 
  "JP.CBIJ.BXY": {
    "weight": 0.8360542988380649
  }, 
  "KN.CHM.BXY": {
    "weight": 0.08849046414644784
  }, 
  "KN.EKS2.BXY": {
    "weight": 0.09135734890015872
  }, 
  "KN.KBK.BXY": {
    "weight": 0.0882892124996381
  }, 
  "KN.KZA.BXY": {
    "weight": 0.08948583406464101
  }, 
  "KN.TKM2.BXY": {
    "weight": 0.08919071657742476
  }, 
  "KN.USP.BXY": {
    "weight": 0.08929622387668319
  }, 
  "KR.ANVS.BXY": {
    "weight": 0.10558939665479945
  }, 
  "KR.ARLS.BXY": {
    "weight": 0.09091993839932073
  }, 
  "KR.NRN.BXY": {
    "weight": 0.09481430094690547
  }, 
  "KZ.ABKAR.BXY": {
    "weight": 0.45431582786243374
  }, 
  "KZ.AKTO.BXY": {
    "weight": 0.4432601826234902
  }, 
  "KZ.BVAR.BXY": {
    "weight": 0.22415758908824707
  }, 
  "KZ.CHKZ.BXY": {
    "weight": 0.2309861165145932
  }, 
  "KZ.KKAR.BXY": {
    "weight": 0.14127110084711383
  }, 
  "KZ.KNDC.BXY": {
    "weight": 0.09789251502692818
  }, 
  "KZ.VOS.BXY": {
    "weight": 0.21910963742727468
  }, 
  "LB.BMN.BXY": {
    "weight": 0.022848773147704334
  }, 
  "LD.FRNY.BXY": {
    "weight": 0.20113016385033872
  }, 
  "LD.PANJ.BXY": {
    "weight": 0.1998655310859117
  }, 
  "LI.LTH.BXY": {
    "weight": 0.03295323270511264
  }, 
  "MN.BNI.BXY": {
    "weight": 0.16065946776383722
  }, 
  "MN.CEL.BXY": {
    "weight": 0.26548722405246605
  }, 
  "MN.CUC.BXY": {
    "weight": 0.21142731216797428
  }, 
  "MN.DIVS.BXY": {
    "weight": 0.22023690122623202
  }, 
  "MN.IDI.BXY": {
    "weight": 0.5794730120847476
  }, 
  "MN.RTC.BXY": {
    "weight": 0.311112139609769
  }, 
  "MN.TIR.BXY": {
    "weight": 0.21991811215525747
  }, 
  "MN.TRI.BXY": {
    "weight": 0.13704487725322298
  }, 
  "MN.TUE.BXY": {
    "weight": 0.1234568331203128
  }, 
  "MN.VLC.BXY": {
    "weight": 0.13411721601333604
  }, 
  "MN.VSL.BXY": {
    "weight": 0.28008121338567143
  }, 
  "MN.VTS.BXY": {
    "weight": 0.27465778667923524
  }, 
  "NM.PBMO.BXY": {
    "weight": 0.07144712345074004
  }, 
  "NM.PVMO.BXY": {
    "weight": 0.07919098940512831
  }, 
  "NM.SIUC.BXY": {
    "weight": 0.08161152696752107
  }, 
  "NM.USIN.BXY": {
    "weight": 0.09444867078197158
  }, 
  "NM.UTMT.BXY": {
    "weight": 0.0865860725265816
  }, 
  "OE.ARSA.BXY": {
    "weight": 0.16856318890843136
  }, 
  "OE.DAVA.BXY": {
    "weight": 0.12304783479054929
  }, 
  "OE.KBA.BXY": {
    "weight": 0.1362318857321348
  }, 
  "PE.UPAO.BXY": {
    "weight": 0.1685240300464453
  }, 
  "PM.PESTR.BXY": {
    "weight": 0.2472472516283962
  }, 
  "PM.PFVI.BXY": {
    "weight": 0.2506228997711027
  }, 
  "PM.PVAQ.BXY": {
    "weight": 0.2360600199869399
  }, 
  "PS.SYO.BXY": {
    "weight": 1.0
  }, 
  "PS.TSK.BXY": {
    "weight": 0.3449932000616912
  }, 
  "TA.109C.BXY": {
    "weight": 0.016667859369990018
  }, 
  "TA.113A.BXY": {
    "weight": 0.015216391394679141
  }, 
  "TA.120A.BXY": {
    "weight": 0.01042693064195051
  }, 
  "TA.121A.BXY": {
    "weight": 0.009586986688902838
  }, 
  "TA.122A.BXY": {
    "weight": 0.008779959523935189
  }, 
  "TA.123A.BXY": {
    "weight": 0.008374510466210862
  }, 
  "TA.124A.BXY": {
    "weight": 0.007962119931184985
  }, 
  "TA.125A.BXY": {
    "weight": 0.00779356128688805
  }, 
  "TA.126A.BXY": {
    "weight": 0.007750164982442737
  }, 
  "TA.127A.BXY": {
    "weight": 0.0077778357498132855
  }, 
  "TA.128A.BXY": {
    "weight": 0.008058648177863444
  }, 
  "TA.129A.BXY": {
    "weight": 0.00835509950481837
  }, 
  "TA.130A.BXY": {
    "weight": 0.009057167245025642
  }, 
  "TA.131A.BXY": {
    "weight": 0.00959649435321921
  }, 
  "TA.214A.BXY": {
    "weight": 0.016148261764355628
  }, 
  "TA.220A.BXY": {
    "weight": 0.011167162587670709
  }, 
  "TA.221A.BXY": {
    "weight": 0.010205080757899422
  }, 
  "TA.222A.BXY": {
    "weight": 0.009477934115677331
  }, 
  "TA.223A.BXY": {
    "weight": 0.009102042660190357
  }, 
  "TA.224A.BXY": {
    "weight": 0.00855231343677849
  }, 
  "TA.225A.BXY": {
    "weight": 0.008297696963771303
  }, 
  "TA.226B.BXY": {
    "weight": 0.008233581956616446
  }, 
  "TA.227A.BXY": {
    "weight": 0.008341299228642999
  }, 
  "TA.228A.BXY": {
    "weight": 0.008432309971883777
  }, 
  "TA.229A.BXY": {
    "weight": 0.008962509203498831
  }, 
  "TA.230A.BXY": {
    "weight": 0.009576804522157409
  }, 
  "TA.231A.BXY": {
    "weight": 0.010391932263670576
  }, 
  "TA.232A.BXY": {
    "weight": 0.011434845079290486
  }, 
  "TA.319A.BXY": {
    "weight": 0.013077522071008566
  }, 
  "TA.320A.BXY": {
    "weight": 0.012122393824195004
  }, 
  "TA.324A.BXY": {
    "weight": 0.009262831429083037
  }, 
  "TA.325A.BXY": {
    "weight": 0.009157572257706716
  }, 
  "TA.326A.BXY": {
    "weight": 0.0090479379371356
  }, 
  "TA.327A.BXY": {
    "weight": 0.008998766441053638
  }, 
  "TA.328A.BXY": {
    "weight": 0.009123823744077546
  }, 
  "TA.329A.BXY": {
    "weight": 0.009371336374951278
  }, 
  "TA.330A.BXY": {
    "weight": 0.01007053679776788
  }, 
  "TA.331A.BXY": {
    "weight": 0.011021441888852903
  }, 
  "TA.332A.BXY": {
    "weight": 0.011939299030349418
  }, 
  "TA.425A.BXY": {
    "weight": 0.009996250425540667
  }, 
  "TA.426A.BXY": {
    "weight": 0.009959006667118695
  }, 
  "TA.427A.BXY": {
    "weight": 0.009695197786160833
  }, 
  "TA.428A.BXY": {
    "weight": 0.01004788923874682
  }, 
  "TA.429A.BXY": {
    "weight": 0.010608098225904522
  }, 
  "TA.430A.BXY": {
    "weight": 0.010880177696757105
  }, 
  "TA.431A.BXY": {
    "weight": 0.011745406376510597
  }, 
  "TA.432A.BXY": {
    "weight": 0.012648851797284042
  }, 
  "TA.526A.BXY": {
    "weight": 0.011044848554077547
  }, 
  "TA.527A.BXY": {
    "weight": 0.01085105497775156
  }, 
  "TA.528A.BXY": {
    "weight": 0.01096491078826728
  }, 
  "TA.529A.BXY": {
    "weight": 0.011284574388317321
  }, 
  "TA.530A.BXY": {
    "weight": 0.011902012921222052
  }, 
  "TA.531A.BXY": {
    "weight": 0.01279979652557564
  }, 
  "TA.532A.BXY": {
    "weight": 0.013917207713132585
  }, 
  "TA.626A.BXY": {
    "weight": 0.012163488167725913
  }, 
  "TA.627A.BXY": {
    "weight": 0.012359496900567027
  }, 
  "TA.628A.BXY": {
    "weight": 0.01237066283704903
  }, 
  "TA.631A.BXY": {
    "weight": 0.014548372166759851
  }, 
  "TA.632A.BXY": {
    "weight": 0.015722020733774784
  }, 
  "TA.732A.BXY": {
    "weight": 0.01786954608687807
  }, 
  "TA.A19A.BXY": {
    "weight": 0.020380306500580543
  }, 
  "TA.A20A.BXY": {
    "weight": 0.018749941018220622
  }, 
  "TA.A26A.BXY": {
    "weight": 0.018483085485886872
  }, 
  "TA.A27A.BXY": {
    "weight": 0.020062483797224116
  }, 
  "TA.A29A.BXY": {
    "weight": 0.025713955843926266
  }, 
  "TA.ABTX.BXY": {
    "weight": 0.01066448892386526
  }, 
  "TA.B19A.BXY": {
    "weight": 0.018888978387935837
  }, 
  "TA.B20A.BXY": {
    "weight": 0.0172843948326156
  }, 
  "TA.B21A.BXY": {
    "weight": 0.016075150180272925
  }, 
  "TA.B22A.BXY": {
    "weight": 0.014992347033145071
  }, 
  "TA.B25A.BXY": {
    "weight": 0.015222658742182524
  }, 
  "TA.B29A.BXY": {
    "weight": 0.02307052099186423
  }, 
  "TA.BGNE.BXY": {
    "weight": 0.013018181758666807
  }, 
  "TA.BRSD.BXY": {
    "weight": 0.014063192296811198
  }, 
  "TA.C19A.BXY": {
    "weight": 0.01672626767131713
  }, 
  "TA.C20A.BXY": {
    "weight": 0.015112602690261889
  }, 
  "TA.C21A.BXY": {
    "weight": 0.014450790978768923
  }, 
  "TA.C23A.BXY": {
    "weight": 0.013463631328248389
  }, 
  "TA.C25A.BXY": {
    "weight": 0.01369697002518908
  }, 
  "TA.C30A.BXY": {
    "weight": 0.023282357312500463
  }, 
  "TA.D19A.BXY": {
    "weight": 0.014974230772713332
  }, 
  "TA.D20A.BXY": {
    "weight": 0.013811075219890466
  }, 
  "TA.D23A.BXY": {
    "weight": 0.012129593496048079
  }, 
  "TA.D24A.BXY": {
    "weight": 0.012038916946328724
  }, 
  "TA.D25A.BXY": {
    "weight": 0.012450785181099195
  }, 
  "TA.D26A.BXY": {
    "weight": 0.012823326899393306
  }, 
  "TA.D27A.BXY": {
    "weight": 0.013962174615825482
  }, 
  "TA.D29A.BXY": {
    "weight": 0.017510326951810845
  }, 
  "TA.D30A.BXY": {
    "weight": 0.02017835836913509
  }, 
  "TA.E19A.BXY": {
    "weight": 0.013393806643081279
  }, 
  "TA.E22A.BXY": {
    "weight": 0.011056370380858549
  }, 
  "TA.E23A.BXY": {
    "weight": 0.010990268786897982
  }, 
  "TA.E24A.BXY": {
    "weight": 0.011091231733782429
  }, 
  "TA.E25A.BXY": {
    "weight": 0.011268395899378445
  }, 
  "TA.E26A.BXY": {
    "weight": 0.01179358110453826
  }, 
  "TA.E29A.BXY": {
    "weight": 0.016183203993690904
  }, 
  "TA.F19A.BXY": {
    "weight": 0.012598945597446117
  }, 
  "TA.F21A.BXY": {
    "weight": 0.010785621963986542
  }, 
  "TA.F22A.BXY": {
    "weight": 0.010269170089393109
  }, 
  "TA.F23A.BXY": {
    "weight": 0.009956642329576125
  }, 
  "TA.F24A.BXY": {
    "weight": 0.010073746378538704
  }, 
  "TA.F25A.BXY": {
    "weight": 0.010415775031619131
  }, 
  "TA.F26A.BXY": {
    "weight": 0.010724191841032779
  }, 
  "TA.F27A.BXY": {
    "weight": 0.01125057358838235
  }, 
  "TA.G22A.BXY": {
    "weight": 0.00964897724612303
  }, 
  "TA.G23A.BXY": {
    "weight": 0.00938211513074231
  }, 
  "TA.G24A.BXY": {
    "weight": 0.009481842706520898
  }, 
  "TA.G25A.BXY": {
    "weight": 0.009568875114597144
  }, 
  "TA.G26A.BXY": {
    "weight": 0.010080803374640296
  }, 
  "TA.G27A.BXY": {
    "weight": 0.010678986347004623
  }, 
  "TA.G30A.BXY": {
    "weight": 0.014627259945656392
  }, 
  "TA.H17A.BXY": {
    "weight": 0.01322597092673902
  }, 
  "TA.H18A.BXY": {
    "weight": 0.012073063350118011
  }, 
  "TA.H21A.BXY": {
    "weight": 0.009447523473858126
  }, 
  "TA.H22A.BXY": {
    "weight": 0.00908391892777442
  }, 
  "TA.H23A.BXY": {
    "weight": 0.008794815799700382
  }, 
  "TA.H24A.BXY": {
    "weight": 0.008907597992237498
  }, 
  "TA.H25A.BXY": {
    "weight": 0.00895799122938503
  }, 
  "TA.H26A.BXY": {
    "weight": 0.00928704922821446
  }, 
  "TA.H27A.BXY": {
    "weight": 0.009743031658727136
  }, 
  "TA.I17A.BXY": {
    "weight": 0.012744424404576607
  }, 
  "TA.I21A.BXY": {
    "weight": 0.008954931510066204
  }, 
  "TA.I22A.BXY": {
    "weight": 0.00859577357548875
  }, 
  "TA.I24A.BXY": {
    "weight": 0.008211598733417235
  }, 
  "TA.I25A.BXY": {
    "weight": 0.008437175840129207
  }, 
  "TA.I26A.BXY": {
    "weight": 0.008749244236130384
  }, 
  "TA.I28A.BXY": {
    "weight": 0.00995861096414987
  }, 
  "TA.I30A.BXY": {
    "weight": 0.012398504214420267
  }, 
  "TA.J19A.BXY": {
    "weight": 0.010096764708424926
  }, 
  "TA.J20A.BXY": {
    "weight": 0.009219557504177682
  }, 
  "TA.J21A.BXY": {
    "weight": 0.008748802412135994
  }, 
  "TA.J22A.BXY": {
    "weight": 0.008283883076935342
  }, 
  "TA.J24A.BXY": {
    "weight": 0.007876060607014288
  }, 
  "TA.J25A.BXY": {
    "weight": 0.007998127383560684
  }, 
  "TA.J26A.BXY": {
    "weight": 0.008158311931731516
  }, 
  "TA.J27A.BXY": {
    "weight": 0.008674547579690033
  }, 
  "TA.J28A.BXY": {
    "weight": 0.00941941687804679
  }, 
  "TA.J29A.BXY": {
    "weight": 0.010445075176230648
  }, 
  "TA.J30A.BXY": {
    "weight": 0.011678863286654842
  }, 
  "TA.K21A.BXY": {
    "weight": 0.008243138768739559
  }, 
  "TA.K22A.BXY": {
    "weight": 0.00789358234251107
  }, 
  "TA.K23A.BXY": {
    "weight": 0.0076673988799096275
  }, 
  "TA.K25A.BXY": {
    "weight": 0.007557302018367944
  }, 
  "TA.K28A.BXY": {
    "weight": 0.008816937069727294
  }, 
  "TA.K29A.BXY": {
    "weight": 0.009956328331522784
  }, 
  "TA.K30A.BXY": {
    "weight": 0.010921013941920656
  }, 
  "TA.KSCO.BXY": {
    "weight": 0.006767424097866223
  }, 
  "TA.L18A.BXY": {
    "weight": 0.010581922936774527
  }, 
  "TA.L19A.BXY": {
    "weight": 0.009802937802888687
  }, 
  "TA.L20A.BXY": {
    "weight": 0.008740399733939901
  }, 
  "TA.L22A.BXY": {
    "weight": 0.007587986774212302
  }, 
  "TA.L23A.BXY": {
    "weight": 0.007397879862092419
  }, 
  "TA.L24A.BXY": {
    "weight": 0.007255529829990954
  }, 
  "TA.L25A.BXY": {
    "weight": 0.00733249032593867
  }, 
  "TA.L26A.BXY": {
    "weight": 0.007485542659544664
  }, 
  "TA.L27A.BXY": {
    "weight": 0.00783180071340441
  }, 
  "TA.L28A.BXY": {
    "weight": 0.008302477977204377
  }, 
  "TA.L29A.BXY": {
    "weight": 0.00931735847274856
  }, 
  "TA.L30A.BXY": {
    "weight": 0.010253264091179805
  }, 
  "TA.M02C.BXY": {
    "weight": 0.046229257174885095
  }, 
  "TA.M17A.BXY": {
    "weight": 0.011303978177607563
  }, 
  "TA.M19A.BXY": {
    "weight": 0.009331592953780164
  }, 
  "TA.M20A.BXY": {
    "weight": 0.008416568603849
  }, 
  "TA.M22A.BXY": {
    "weight": 0.007426877360935423
  }, 
  "TA.M23A.BXY": {
    "weight": 0.007164112770663097
  }, 
  "TA.M24A.BXY": {
    "weight": 0.007035264208381774
  }, 
  "TA.M25A.BXY": {
    "weight": 0.007042305653618731
  }, 
  "TA.M27A.BXY": {
    "weight": 0.007553894928088613
  }, 
  "TA.M28A.BXY": {
    "weight": 0.008133782575415534
  }, 
  "TA.M29A.BXY": {
    "weight": 0.008766121669729005
  }, 
  "TA.M30A.BXY": {
    "weight": 0.009793782263648382
  }, 
  "TA.M31A.BXY": {
    "weight": 0.011150957493758638
  }, 
  "TA.MDND.BXY": {
    "weight": 0.01987609222330571
  }, 
  "TA.MSTX.BXY": {
    "weight": 0.007180885237768685
  }, 
  "TA.N20A.BXY": {
    "weight": 0.008272149887621372
  }, 
  "TA.N22A.BXY": {
    "weight": 0.0071917753742717985
  }, 
  "TA.N23A.BXY": {
    "weight": 0.007046242064396248
  }, 
  "TA.N24A.BXY": {
    "weight": 0.0068406292791890425
  }, 
  "TA.N25A.BXY": {
    "weight": 0.006841905741058858
  }, 
  "TA.N26A.BXY": {
    "weight": 0.006997807380819908
  }, 
  "TA.N27A.BXY": {
    "weight": 0.007226971028530498
  }, 
  "TA.N28A.BXY": {
    "weight": 0.007740041071963525
  }, 
  "TA.N32A.BXY": {
    "weight": 0.012263431183708545
  }, 
  "TA.O19A.BXY": {
    "weight": 0.008928152876815676
  }, 
  "TA.O20A.BXY": {
    "weight": 0.00808264670666979
  }, 
  "TA.O21A.BXY": {
    "weight": 0.007556479851533577
  }, 
  "TA.O22A.BXY": {
    "weight": 0.007075198627108614
  }, 
  "TA.O23A.BXY": {
    "weight": 0.0068695474713309545
  }, 
  "TA.O24A.BXY": {
    "weight": 0.006683940578590337
  }, 
  "TA.O25A.BXY": {
    "weight": 0.006659460702539775
  }, 
  "TA.O26A.BXY": {
    "weight": 0.006812438928140836
  }, 
  "TA.O27A.BXY": {
    "weight": 0.007072336748102364
  }, 
  "TA.O29A.BXY": {
    "weight": 0.008155146812709013
  }, 
  "TA.O31A.BXY": {
    "weight": 0.00997496125156892
  }, 
  "TA.P19A.BXY": {
    "weight": 0.008642476119508784
  }, 
  "TA.P20A.BXY": {
    "weight": 0.008084850373613103
  }, 
  "TA.P22A.BXY": {
    "weight": 0.00705979001868643
  }, 
  "TA.P23A.BXY": {
    "weight": 0.00669301047163066
  }, 
  "TA.P24A.BXY": {
    "weight": 0.00654928804974671
  }, 
  "TA.P25A.BXY": {
    "weight": 0.00653515963307585
  }, 
  "TA.P26A.BXY": {
    "weight": 0.006654124103696929
  }, 
  "TA.P27A.BXY": {
    "weight": 0.0068845189086331185
  }, 
  "TA.P28A.BXY": {
    "weight": 0.0072915361506274
  }, 
  "TA.P29A.BXY": {
    "weight": 0.007892419747515244
  }, 
  "TA.P30A.BXY": {
    "weight": 0.008548555092541852
  }, 
  "TA.P31A.BXY": {
    "weight": 0.009682908491281396
  }, 
  "TA.P32A.BXY": {
    "weight": 0.01109059670249162
  }, 
  "TA.P33A.BXY": {
    "weight": 0.013187074982776128
  }, 
  "TA.Q16A.BXY": {
    "weight": 0.011224800174662451
  }, 
  "TA.Q20A.BXY": {
    "weight": 0.007930950337226711
  }, 
  "TA.Q21A.BXY": {
    "weight": 0.007400617549115817
  }, 
  "TA.Q22A.BXY": {
    "weight": 0.007031281349493624
  }, 
  "TA.Q23A.BXY": {
    "weight": 0.006628731448419376
  }, 
  "TA.Q24A.BXY": {
    "weight": 0.0064954643092353034
  }, 
  "TA.Q25A.BXY": {
    "weight": 0.006439789467782686
  }, 
  "TA.Q26A.BXY": {
    "weight": 0.006514915123520123
  }, 
  "TA.Q28A.BXY": {
    "weight": 0.007145745961929233
  }, 
  "TA.Q29A.BXY": {
    "weight": 0.0077032540720734875
  }, 
  "TA.Q30A.BXY": {
    "weight": 0.008446563906252669
  }, 
  "TA.Q31A.BXY": {
    "weight": 0.009523874402428602
  }, 
  "TA.R11A.BXY": {
    "weight": 0.01699883216121047
  }, 
  "TA.R20A.BXY": {
    "weight": 0.007935095423100868
  }, 
  "TA.R21A.BXY": {
    "weight": 0.0073468105879464255
  }, 
  "TA.R22A.BXY": {
    "weight": 0.006907307763924967
  }, 
  "TA.R23A.BXY": {
    "weight": 0.006564401467355447
  }, 
  "TA.R24A.BXY": {
    "weight": 0.006418562807810985
  }, 
  "TA.R25A.BXY": {
    "weight": 0.006362433301035734
  }, 
  "TA.R26A.BXY": {
    "weight": 0.006456654712345325
  }, 
  "TA.R27A.BXY": {
    "weight": 0.006617263850257385
  }, 
  "TA.R28A.BXY": {
    "weight": 0.007054201858396467
  }, 
  "TA.R29A.BXY": {
    "weight": 0.00750663981738899
  }, 
  "TA.R30A.BXY": {
    "weight": 0.00827235936330659
  }, 
  "TA.R31A.BXY": {
    "weight": 0.009200873111622135
  }, 
  "TA.S21A.BXY": {
    "weight": 0.007483001263890252
  }, 
  "TA.S22A.BXY": {
    "weight": 0.006925418379872726
  }, 
  "TA.S23A.BXY": {
    "weight": 0.006598070564062158
  }, 
  "TA.S24A.BXY": {
    "weight": 0.006408903738616496
  }, 
  "TA.S26A.BXY": {
    "weight": 0.006410917902140279
  }, 
  "TA.S27A.BXY": {
    "weight": 0.00654521727919779
  }, 
  "TA.S28A.BXY": {
    "weight": 0.0069489815631170815
  }, 
  "TA.S29A.BXY": {
    "weight": 0.007450606309603437
  }, 
  "TA.S30A.BXY": {
    "weight": 0.008021332696898127
  }, 
  "TA.S31A.BXY": {
    "weight": 0.009196059771475482
  }, 
  "TA.S32A.BXY": {
    "weight": 0.010071433083236972
  }, 
  "TA.SFIN.BXY": {
    "weight": 0.11041520181607388
  }, 
  "TA.SPMN.BXY": {
    "weight": 0.06439455807998529
  }, 
  "TA.T21A.BXY": {
    "weight": 0.00733751428647528
  }, 
  "TA.T22A.BXY": {
    "weight": 0.006978667207427284
  }, 
  "TA.T23A.BXY": {
    "weight": 0.006619500156410101
  }, 
  "TA.T24B.BXY": {
    "weight": 0.006445093793747769
  }, 
  "TA.T25A.BXY": {
    "weight": 0.006336616794708301
  }, 
  "TA.T26A.BXY": {
    "weight": 0.006386550662403477
  }, 
  "TA.T27A.BXY": {
    "weight": 0.0065905983056308345
  }, 
  "TA.T28A.BXY": {
    "weight": 0.00683210932271482
  }, 
  "TA.T29A.BXY": {
    "weight": 0.007310068543204889
  }, 
  "TA.T30A.BXY": {
    "weight": 0.007945565573731498
  }, 
  "TA.T31A.BXY": {
    "weight": 0.00891622667886181
  }, 
  "TA.T32A.BXY": {
    "weight": 0.01007380110415544
  }, 
  "TA.TUL1.BXY": {
    "weight": 0.02055916220627249
  }, 
  "TA.U15A.BXY": {
    "weight": 0.0122359322466992
  }, 
  "TA.U20A.BXY": {
    "weight": 0.008135841139143741
  }, 
  "TA.U21A.BXY": {
    "weight": 0.007476174032362372
  }, 
  "TA.U22A.BXY": {
    "weight": 0.007015199116911459
  }, 
  "TA.U23A.BXY": {
    "weight": 0.0067338935023070826
  }, 
  "TA.U24A.BXY": {
    "weight": 0.006470026462616038
  }, 
  "TA.U25A.BXY": {
    "weight": 0.006377434535592137
  }, 
  "TA.U26A.BXY": {
    "weight": 0.006404643692824171
  }, 
  "TA.U27A.BXY": {
    "weight": 0.006587375872963358
  }, 
  "TA.U28A.BXY": {
    "weight": 0.00681291075778646
  }, 
  "TA.U29A.BXY": {
    "weight": 0.007352178585392996
  }, 
  "TA.U30A.BXY": {
    "weight": 0.007849383981679139
  }, 
  "TA.U31A.BXY": {
    "weight": 0.008728830798761597
  }, 
  "TA.V20A.BXY": {
    "weight": 0.008205274882436952
  }, 
  "TA.V21A.BXY": {
    "weight": 0.007575541573201245
  }, 
  "TA.V22A.BXY": {
    "weight": 0.007118145367990217
  }, 
  "TA.V23A.BXY": {
    "weight": 0.00682515074849577
  }, 
  "TA.V24A.BXY": {
    "weight": 0.0065657262980665845
  }, 
  "TA.V25A.BXY": {
    "weight": 0.0064576906067331545
  }, 
  "TA.V26A.BXY": {
    "weight": 0.006472391705882306
  }, 
  "TA.V27A.BXY": {
    "weight": 0.006660710911885055
  }, 
  "TA.V28A.BXY": {
    "weight": 0.006886718742323591
  }, 
  "TA.V29A.BXY": {
    "weight": 0.00724618765347836
  }, 
  "TA.V30A.BXY": {
    "weight": 0.007903707430997668
  }, 
  "TA.W13A.BXY": {
    "weight": 0.013577017790074438
  }, 
  "TA.W18A.BXY": {
    "weight": 0.009642486290105638
  }, 
  "TA.W20A.BXY": {
    "weight": 0.008439462780406018
  }, 
  "TA.W21A.BXY": {
    "weight": 0.007775864091350324
  }, 
  "TA.W22A.BXY": {
    "weight": 0.007310245674217412
  }, 
  "TA.W23A.BXY": {
    "weight": 0.0069530978883707946
  }, 
  "TA.W24A.BXY": {
    "weight": 0.0067083342402926485
  }, 
  "TA.W25A.BXY": {
    "weight": 0.006570814007621639
  }, 
  "TA.W26A.BXY": {
    "weight": 0.006615501518854424
  }, 
  "TA.W27A.BXY": {
    "weight": 0.006737722624123879
  }, 
  "TA.W28A.BXY": {
    "weight": 0.006986733067249157
  }, 
  "TA.W29A.BXY": {
    "weight": 0.007311740440809697
  }, 
  "TA.W31A.BXY": {
    "weight": 0.008828082475229213
  }, 
  "TA.WHTX.BXY": {
    "weight": 0.017035930099527318
  }, 
  "TA.X16A.BXY": {
    "weight": 0.011852269863000446
  }, 
  "TA.X18A.BXY": {
    "weight": 0.010155265971348604
  }, 
  "TA.X20A.BXY": {
    "weight": 0.008689690897205692
  }, 
  "TA.X21A.BXY": {
    "weight": 0.008150818833158562
  }, 
  "TA.X22A.BXY": {
    "weight": 0.007602657620956956
  }, 
  "TA.X23A.BXY": {
    "weight": 0.007160657622917639
  }, 
  "TA.X24A.BXY": {
    "weight": 0.006913724514635214
  }, 
  "TA.X25A.BXY": {
    "weight": 0.006787064744078976
  }, 
  "TA.X26A.BXY": {
    "weight": 0.006766597082385101
  }, 
  "TA.X27A.BXY": {
    "weight": 0.006844971979090007
  }, 
  "TA.X28A.BXY": {
    "weight": 0.007193327778067262
  }, 
  "TA.X29A.BXY": {
    "weight": 0.007479498094459309
  }, 
  "TA.X30A.BXY": {
    "weight": 0.008084698706522718
  }, 
  "TA.X31A.BXY": {
    "weight": 0.008960797925722113
  }, 
  "TA.Y12C.BXY": {
    "weight": 0.014429597967854577
  }, 
  "TA.Y14A.BXY": {
    "weight": 0.013536953463360911
  }, 
  "TA.Y20A.BXY": {
    "weight": 0.008945900786785546
  }, 
  "TA.Y21A.BXY": {
    "weight": 0.008299103651055585
  }, 
  "TA.Y22A.BXY": {
    "weight": 0.007855956094492272
  }, 
  "TA.Y22D.BXY": {
    "weight": 0.007755693393827409
  }, 
  "TA.Y23A.BXY": {
    "weight": 0.007394375832056798
  }, 
  "TA.Y24A.BXY": {
    "weight": 0.0071828247477736685
  }, 
  "TA.Y25A.BXY": {
    "weight": 0.007033717458464841
  }, 
  "TA.Y26A.BXY": {
    "weight": 0.00700691270901509
  }, 
  "TA.Y27A.BXY": {
    "weight": 0.00711574335426215
  }, 
  "TA.Y28A.BXY": {
    "weight": 0.007405678207027438
  }, 
  "TA.Y29A.BXY": {
    "weight": 0.007734167599208205
  }, 
  "TA.Y30A.BXY": {
    "weight": 0.008305161220483219
  }, 
  "TA.Y31A.BXY": {
    "weight": 0.008908706064816897
  }, 
  "TA.Z14A.BXY": {
    "weight": 0.014020852946747932
  }, 
  "TA.Z20A.BXY": {
    "weight": 0.009782997924866366
  }, 
  "TA.Z21A.BXY": {
    "weight": 0.008772084187950278
  }, 
  "TA.Z22A.BXY": {
    "weight": 0.008294222675689673
  }, 
  "TA.Z23A.BXY": {
    "weight": 0.00787101459497403
  }, 
  "TA.Z24A.BXY": {
    "weight": 0.007489698297424976
  }, 
  "TA.Z25A.BXY": {
    "weight": 0.007377867681809039
  }, 
  "TA.Z26A.BXY": {
    "weight": 0.0073339499797575505
  }, 
  "TA.Z27A.BXY": {
    "weight": 0.007391374038989208
  }, 
  "TA.Z28A.BXY": {
    "weight": 0.0076597277861589
  }, 
  "TA.Z29A.BXY": {
    "weight": 0.008028467688226857
  }, 
  "TA.Z30A.BXY": {
    "weight": 0.008428905905896055
  }, 
  "TA.Z31A.BXY": {
    "weight": 0.009417802986549222
  }, 
  "TA.Z32A.BXY": {
    "weight": 0.01037402060648071
  }, 
  "TW.KMNB.BXY": {
    "weight": 0.154293573650047
  }, 
  "TW.NACB.BXY": {
    "weight": 0.13187395962547582
  }, 
  "TW.SSLB.BXY": {
    "weight": 0.12992052955503888
  }, 
  "TW.TPUB.BXY": {
    "weight": 0.13145857426459587
  }, 
  "TW.TWGB.BXY": {
    "weight": 0.13449730927933384
  }, 
  "TW.YHNB.BXY": {
    "weight": 0.13272522543516485
  }, 
  "TW.YULB.BXY": {
    "weight": 0.1314941816131629
  }, 
  "UO.DBO.BXY": {
    "weight": 0.0460026220698853
  }, 
  "US.AGMN.BXY": {
    "weight": 0.04425691160312653
  }, 
  "US.AHID.BXY": {
    "weight": 0.012743045547157312
  }, 
  "US.BMO.BXY": {
    "weight": 0.028376952845158922
  }, 
  "US.BRAL.BXY": {
    "weight": 0.19494478156338516
  }, 
  "US.BW06.BXY": {
    "weight": 0.010389002655676082
  }, 
  "US.COWI.BXY": {
    "weight": 0.15580273047613125
  }, 
  "US.DGMT.BXY": {
    "weight": 0.015302599331045087
  }, 
  "US.DUG.BXY": {
    "weight": 0.0145075759835094
  }, 
  "US.EGAK.BXY": {
    "weight": 0.10312854539426408
  }, 
  "US.EGMT.BXY": {
    "weight": 0.01904665444093255
  }, 
  "US.ELK.BXY": {
    "weight": 0.019722483111587745
  }, 
  "US.ERPA.BXY": {
    "weight": 0.17644939338623045
  }, 
  "US.EYMN.BXY": {
    "weight": 0.12092237246816971
  }, 
  "US.HAWA.BXY": {
    "weight": 0.032920798488753435
  }, 
  "US.HLID.BXY": {
    "weight": 0.021064726041297915
  }, 
  "US.ISCO.BXY": {
    "weight": 0.006709852864186128
  }, 
  "US.JCT.BXY": {
    "weight": 0.01336608243935735
  }, 
  "US.JFWS.BXY": {
    "weight": 0.09277597020938497
  }, 
  "US.KSU1.BXY": {
    "weight": 0.016715447613335037
  }, 
  "US.KVTX.BXY": {
    "weight": 0.03276242085181175
  }, 
  "US.LAO.BXY": {
    "weight": 0.011557856818675934
  }, 
  "US.LBNH.BXY": {
    "weight": 0.21522284977404676
  }, 
  "US.LONY.BXY": {
    "weight": 0.1938017121044602
  }, 
  "US.LRAL.BXY": {
    "weight": 0.14123353353189225
  }, 
  "US.MCWV.BXY": {
    "weight": 0.17263338702478662
  }, 
  "US.MIAR.BXY": {
    "weight": 0.04004202363193839
  }, 
  "US.MNTX.BXY": {
    "weight": 0.008906687883138961
  }, 
  "US.MSO.BXY": {
    "weight": 0.026791592367555083
  }, 
  "US.MVCO.BXY": {
    "weight": 0.008032672622472661
  }, 
  "US.NEW.BXY": {
    "weight": 0.038916447702911076
  }, 
  "US.NLWA.BXY": {
    "weight": 0.0509235627887177
  }, 
  "US.PKME.BXY": {
    "weight": 0.30818623369958825
  }, 
  "US.SCIA.BXY": {
    "weight": 0.045283195607244794
  }, 
  "US.SDCO.BXY": {
    "weight": 0.006465995556997301
  }, 
  "US.WRAK.BXY": {
    "weight": 0.21646615932103197
  }, 
  "US.WUAZ.BXY": {
    "weight": 0.011316166721090716
  }, 
  "US.WVOR.BXY": {
    "weight": 0.028295379858608586
  }, 
  "UU.SRU.BXY": {
    "weight": 0.010355843638377419
  }, 
  "UW.BLOW.BXY": {
    "weight": 0.03788373300514259
  }, 
  "UW.BRAN.BXY": {
    "weight": 0.030259729327491897
  }, 
  "UW.FISH.BXY": {
    "weight": 0.04553562113673881
  }, 
  "UW.IRON.BXY": {
    "weight": 0.02860936289474207
  }, 
  "UW.IZEE.BXY": {
    "weight": 0.030606747783226487
  }, 
  "UW.KENT.BXY": {
    "weight": 0.033133698799968254
  }, 
  "UW.LCCR.BXY": {
    "weight": 0.03908871773034019
  }, 
  "UW.LEBA.BXY": {
    "weight": 0.04636936984667755
  }, 
  "UW.LTY.BXY": {
    "weight": 0.03657332467066292
  }, 
  "UW.MRBL.BXY": {
    "weight": 0.04378818244924277
  }, 
  "UW.OMAK.BXY": {
    "weight": 0.039696795879364
  }, 
  "UW.PASS.BXY": {
    "weight": 0.04892540936347138
  }, 
  "UW.STOR.BXY": {
    "weight": 0.039838306108011104
  }, 
  "UW.TREE.BXY": {
    "weight": 0.03416383123425237
  }, 
  "UW.TUCA.BXY": {
    "weight": 0.03219739357687936
  }, 
  "UW.UMAT.BXY": {
    "weight": 0.030667514222455637
  }, 
  "UW.WOLL.BXY": {
    "weight": 0.034122880981656355
  }, 
  "UW.YACT.BXY": {
    "weight": 0.03917308663898223
  }, 
  "XD.PSP03.BXY": {
    "weight": 0.49605484089896884
  }, 
  "XH.ESP01.BXY": {
    "weight": 0.04439164864160309
  }, 
  "XH.ESP04.BXY": {
    "weight": 0.037515650195662706
  }, 
  "XH.ESP06.BXY": {
    "weight": 0.03435447203863492
  }, 
  "XH.ESP07.BXY": {
    "weight": 0.03315129836395482
  }, 
  "XH.ESP08.BXY": {
    "weight": 0.036640628759434433
  }, 
  "XH.ESP09.BXY": {
    "weight": 0.036360318902266986
  }, 
  "XH.ESP10.BXY": {
    "weight": 0.03498995639200966
  }, 
  "XH.ESP11.BXY": {
    "weight": 0.03261315177917459
  }, 
  "XH.ESP12.BXY": {
    "weight": 0.032538059672542384
  }, 
  "YT.DUFK.BXY": {
    "weight": 0.9990749828391733
  }, 
  "YT.HOWD.BXY": {
    "weight": 0.9999889051752314
  }, 
  "YT.LONW.BXY": {
    "weight": 0.9149031935792123
  }, 
  "YT.MPAT.BXY": {
    "weight": 1.0
  }, 
  "YT.PECA.BXY": {
    "weight": 0.9990646079942661
  }, 
  "YT.WAIS.BXY": {
    "weight": 0.9999999857907673
  }, 
  "ZL.ABRA.BXY": {
    "weight": 0.029905395070734274
  }, 
  "ZL.ARRO.BXY": {
    "weight": 0.02926511722263274
  }, 
  "ZL.BARR.BXY": {
    "weight": 0.029419393394434487
  }, 
  "ZL.BOZA.BXY": {
    "weight": 0.028210933537560687
  }, 
  "ZL.CALI.BXY": {
    "weight": 0.02922173438555496
  }, 
  "ZL.CASP.BXY": {
    "weight": 0.029665023616678058
  }, 
  "ZL.CHIL.BXY": {
    "weight": 0.02867480054224079
  }, 
  "ZL.CHUC.BXY": {
    "weight": 0.028099009408786388
  }, 
  "ZL.CHUM.BXY": {
    "weight": 0.034525277509978906
  }, 
  "ZL.CONE.BXY": {
    "weight": 0.027784852488590292
  }, 
  "ZL.CORT.BXY": {
    "weight": 0.03076618138487425
  }, 
  "ZL.DOCA.BXY": {
    "weight": 0.02862566418073692
  }, 
  "ZL.GUAL.BXY": {
    "weight": 0.028477167176928126
  }, 
  "ZL.LAJA.BXY": {
    "weight": 0.027973882588176832
  }, 
  "ZL.LEON.BXY": {
    "weight": 0.0293852015430216
  }, 
  "ZL.LLAN.BXY": {
    "weight": 0.02964880013841689
  }, 
  "ZL.MONA.BXY": {
    "weight": 0.02798289910271834
  }, 
  "ZL.NIKI.BXY": {
    "weight": 0.027929779300982623
  }, 
  "ZL.NOQE.BXY": {
    "weight": 0.028785164232598567
  }, 
  "ZL.NUEV.BXY": {
    "weight": 0.029426494048704326
  }, 
  "ZL.PACH.BXY": {
    "weight": 0.02893239177831251
  }, 
  "ZL.PATO.BXY": {
    "weight": 0.030316203350080787
  }, 
  "ZL.SASO.BXY": {
    "weight": 0.028578493135166957
  }, 
  "ZL.SECA.BXY": {
    "weight": 0.02824727680621542
  }, 
  "ZL.SOMB.BXY": {
    "weight": 0.02900813730489817
  }, 
  "ZL.TOCO.BXY": {
    "weight": 0.029398092834239376
  }, 
  "ZL.TUCU.BXY": {
    "weight": 0.028295387335362285
  }, 
  "ZL.USPA.BXY": {
    "weight": 0.030125098320314105
  }, 
  "ZL.VELA.BXY": {
    "weight": 0.030033798495142604
  }, 
  "ZL.ZOND.BXY": {
    "weight": 0.028323432220129317
  }
}